htcollector
