Metadata-Version: 2.1
Name: htcollector
Version: 1.0.0
Summary: Tools to log updates from Shelly HT devices
Home-page: https://varkenvarken.github.io/shellyhtcollector2/
Author: varkenvarken
Author-email: test@example.com
License: GPLv3
Platform: UNKNOWN
Classifier: Development Status :: 5 - Production/Stable
Classifier: Programming Language :: Python :: 3.8
Classifier: Programming Language :: Python :: 3.9
Classifier: License :: OSI Approved :: GNU General Public License v3 (GPLv3)
Classifier: Operating System :: OS Independent
Requires-Python: >=3.8
